xsense/__init__.py
xsense/async_xsense.py
xsense/aws_signer.py
xsense/base.py
xsense/device.py
xsense/entity.py
xsense/entity_map.py
xsense/exceptions.py
xsense/house.py
xsense/mapping.py
xsense/mqtt_helper.py
xsense/station.py
xsense/utils.py
xsense/xsense.py
python_xsense-0.0.16.dist-info/METADATA
python_xsense-0.0.16.dist-info/WHEEL
python_xsense-0.0.16.dist-info/top_level.txt
python_xsense-0.0.16.dist-info/RECORD
