Metadata-Version: 2.2
Name: python-xsense
Version: 0.0.16
Summary: XSense Python Module
Home-page: https://github.com/theosnel/python-xsense
Author: Theo Snelleman
Author-email: <python@theo.snelleman.net>
License: MIT
Keywords: python,xsense
Classifier: Development Status :: 3 - Alpha
Classifier: Intended Audience :: Education
Classifier: License :: OSI Approved :: MIT License
Classifier: Programming Language :: Python :: 3
Classifier: Operating System :: OS Independent
Requires-Dist: requests
Requires-Dist: boto3
Requires-Dist: botocore
Requires-Dist: pycognito
Requires-Dist: paho-mqtt>=2.1.0
Provides-Extra: async
Requires-Dist: aiohttp; extra == "async"
Dynamic: author
Dynamic: author-email
Dynamic: classifier
Dynamic: description
Dynamic: home-page
Dynamic: keywords
Dynamic: license
Dynamic: provides-extra
Dynamic: requires-dist
Dynamic: summary
